smsactivate/__init__.py
smsactivate/api.py
smsactivate-1.4.dist-info/METADATA
smsactivate-1.4.dist-info/WHEEL
smsactivate-1.4.dist-info/top_level.txt
smsactivate-1.4.dist-info/RECORD
